<?xml version="1.0" encoding="utf-8" ?><dwsync><file name="core.js" server="93.188.160.104" local="3594688698" remote="3596511120" Dst="-1" /><file name="fullscreen.js" server="93.188.160.104" local="3594688698" remote="3596511120" Dst="-1" /><file name="media.js" server="93.188.160.104" local="3594688698" remote="3596511120" Dst="-1" /><file name="hash.js" server="93.188.160.104" local="3594688698" remote="3596511120" Dst="-1" /><file name="slideshow.js" server="93.188.160.104" local="3594688698" remote="3596511120" Dst="-1" /><file name="thumbs.js" server="93.188.160.104" local="3594688698" remote="3596511120" Dst="-1" /><file name="share.js" server="93.188.160.104" local="3594688698" remote="3596511120" Dst="-1" /><file name="guestures.js" server="93.188.160.104" local="3594688698" remote="3596511120" Dst="-1" /><file name="wheel.js" server="93.188.160.104" local="3594688698" remote="3596511120" Dst="-1" /></dwsync>